mldocs/__init__.py
mldocs/documentation.py
mldocs/tests/__init__.py
mldocs/tests/test_documentation.py
mldocs-0.0.1.dist-info/DESCRIPTION.rst
mldocs-0.0.1.dist-info/METADATA
mldocs-0.0.1.dist-info/RECORD
mldocs-0.0.1.dist-info/WHEEL
mldocs-0.0.1.dist-info/metadata.json
mldocs-0.0.1.dist-info/top_level.txt
