Metadata-Version: 2.0
Name: mldocs
Version: 0.0.1
Summary: Documents the Machine Learning process from data to model and performance.
Home-page: https://github.com/craftworksgmbh/mldocs
Author: Simon Stiebellehner
Author-email: simon.stiebellehner@craftworks.at
License: MIT
Platform: UNKNOWN
Classifier: Programming Language :: Python :: 3
Classifier: License :: OSI Approved :: MIT License
Classifier: Operating System :: OS Independent
Requires-Dist: numpy
Requires-Dist: pandas
Requires-Dist: sklearn
Requires-Dist: scipy
